cmcrameri/__init__.py
cmcrameri/_version.py
cmcrameri/cm.py
cmcrameri/colormaps.png
cmcrameri/cmaps/acton.txt
cmcrameri/cmaps/actonS.txt
cmcrameri/cmaps/bam.txt
cmcrameri/cmaps/bamO.txt
cmcrameri/cmaps/bamako.txt
cmcrameri/cmaps/bamakoS.txt
cmcrameri/cmaps/batlow.txt
cmcrameri/cmaps/batlowK.txt
cmcrameri/cmaps/batlowKS.txt
cmcrameri/cmaps/batlowS.txt
cmcrameri/cmaps/batlowW.txt
cmcrameri/cmaps/batlowWS.txt
cmcrameri/cmaps/berlin.txt
cmcrameri/cmaps/bilbao.txt
cmcrameri/cmaps/bilbaoS.txt
cmcrameri/cmaps/broc.txt
cmcrameri/cmaps/brocO.txt
cmcrameri/cmaps/buda.txt
cmcrameri/cmaps/budaS.txt
cmcrameri/cmaps/bukavu.txt
cmcrameri/cmaps/cork.txt
cmcrameri/cmaps/corkO.txt
cmcrameri/cmaps/davos.txt
cmcrameri/cmaps/davosS.txt
cmcrameri/cmaps/devon.txt
cmcrameri/cmaps/devonS.txt
cmcrameri/cmaps/fes.txt
cmcrameri/cmaps/glasgow.txt
cmcrameri/cmaps/glasgowS.txt
cmcrameri/cmaps/grayC.txt
cmcrameri/cmaps/grayCS.txt
cmcrameri/cmaps/hawaii.txt
cmcrameri/cmaps/hawaiiS.txt
cmcrameri/cmaps/imola.txt
cmcrameri/cmaps/imolaS.txt
cmcrameri/cmaps/lajolla.txt
cmcrameri/cmaps/lajollaS.txt
cmcrameri/cmaps/lapaz.txt
cmcrameri/cmaps/lapazS.txt
cmcrameri/cmaps/lipari.txt
cmcrameri/cmaps/lipariS.txt
cmcrameri/cmaps/lisbon.txt
cmcrameri/cmaps/managua.txt
cmcrameri/cmaps/navia.txt
cmcrameri/cmaps/naviaS.txt
cmcrameri/cmaps/nuuk.txt
cmcrameri/cmaps/nuukS.txt
cmcrameri/cmaps/oleron.txt
cmcrameri/cmaps/oslo.txt
cmcrameri/cmaps/osloS.txt
cmcrameri/cmaps/roma.txt
cmcrameri/cmaps/romaO.txt
cmcrameri/cmaps/tofino.txt
cmcrameri/cmaps/tokyo.txt
cmcrameri/cmaps/tokyoS.txt
cmcrameri/cmaps/turku.txt
cmcrameri/cmaps/turkuS.txt
cmcrameri/cmaps/vanimo.txt
cmcrameri/cmaps/vik.txt
cmcrameri/cmaps/vikO.txt
cmcrameri-1.8.dist-info/LICENSE.txt
cmcrameri-1.8.dist-info/METADATA
cmcrameri-1.8.dist-info/WHEEL
cmcrameri-1.8.dist-info/top_level.txt
cmcrameri-1.8.dist-info/RECORD
