Metadata-Version: 2.1
Name: cmcrameri
Version: 1.8
Summary: Perceptually uniform colormaps by Fabio Crameri
Author-email: Callum Rollo <c.rollo@outlook.com>
License: MIT License
Project-URL: documentation, https://callumrollo.github.io/cmcrameri
Project-URL: homepage, https://pypi.org/project/cmcrameri/
Project-URL: repository, https://github.com/callumrollo/cmcrameri
Classifier: Programming Language :: Python :: 3 :: Only
Classifier: Programming Language :: Python :: 3.6
Classifier: Programming Language :: Python :: 3.7
Classifier: Programming Language :: Python :: 3.8
Classifier: Programming Language :: Python :: 3.9
Classifier: Programming Language :: Python :: 3.10
Classifier: Programming Language :: Python :: 3.11
Classifier: Programming Language :: Python :: 3.12
Requires-Python: >=3.6
License-File: LICENSE.txt
Requires-Dist: matplotlib
Requires-Dist: numpy
Requires-Dist: packaging
